{"trial_id": "08", "hyperparameters": {"space": [{"class_name": "Int", "config": {"name": "num_conv_layers", "default": null, "conditions": [], "min_value": 1, "max_value": 10, "step": 1, "sampling": "linear"}}, {"class_name": "Int", "config": {"name": "kernel_size_0", "default": null, "conditions": [], "min_value": 3, "max_value": 13, "step": 1, "sampling": "linear"}}, {"class_name": "Int", "config": {"name": "filters_0", "default": null, "conditions": [], "min_value": 32, "max_value": 256, "step": 32, "sampling": "linear"}}, {"class_name": "Int", "config": {"name": "kernel_size_1", "default": null, "conditions": [], "min_value": 3, "max_value": 12, "step": 1, "sampling": "linear"}}, {"class_name": "Int", "config": {"name": "filters_1", "default": null, "conditions": [], "min_value": 32, "max_value": 256, "step": 32, "sampling": "linear"}}, {"class_name": "Int", "config": {"name": "kernel_size_2", "default": null, "conditions": [], "min_value": 3, "max_value": 11, "step": 1, "sampling": "linear"}}, {"class_name": "Int", "config": {"name": "filters_2", "default": null, "conditions": [], "min_value": 32, "max_value": 256, "step": 32, "sampling": "linear"}}, {"class_name": "Int", "config": {"name": "kernel_size_3", "default": null, "conditions": [], "min_value": 3, "max_value": 10, "step": 1, "sampling": "linear"}}, {"class_name": "Int", "config": {"name": "filters_3", "default": null, "conditions": [], "min_value": 32, "max_value": 256, "step": 32, "sampling": "linear"}}, {"class_name": "Int", "config": {"name": "kernel_size_4", "default": null, "conditions": [], "min_value": 3, "max_value": 9, "step": 1, "sampling": "linear"}}, {"class_name": "Int", "config": {"name": "filters_4", "default": null, "conditions": [], "min_value": 32, "max_value": 256, "step": 32, "sampling": "linear"}}, {"class_name": "Int", "config": {"name": "kernel_size_5", "default": null, "conditions": [], "min_value": 3, "max_value": 8, "step": 1, "sampling": "linear"}}, {"class_name": "Int", "config": {"name": "filters_5", "default": null, "conditions": [], "min_value": 32, "max_value": 256, "step": 32, "sampling": "linear"}}, {"class_name": "Int", "config": {"name": "kernel_size_6", "default": null, "conditions": [], "min_value": 3, "max_value": 7, "step": 1, "sampling": "linear"}}, {"class_name": "Int", "config": {"name": "filters_6", "default": null, "conditions": [], "min_value": 32, "max_value": 256, "step": 32, "sampling": "linear"}}, {"class_name": "Int", "config": {"name": "kernel_size_7", "default": null, "conditions": [], "min_value": 3, "max_value": 6, "step": 1, "sampling": "linear"}}, {"class_name": "Int", "config": {"name": "filters_7", "default": null, "conditions": [], "min_value": 32, "max_value": 256, "step": 32, "sampling": "linear"}}, {"class_name": "Int", "config": {"name": "kernel_size_8", "default": null, "conditions": [], "min_value": 3, "max_value": 5, "step": 1, "sampling": "linear"}}, {"class_name": "Int", "config": {"name": "filters_8", "default": null, "conditions": [], "min_value": 32, "max_value": 256, "step": 32, "sampling": "linear"}}, {"class_name": "Int", "config": {"name": "kernel_size_9", "default": null, "conditions": [], "min_value": 3, "max_value": 4, "step": 1, "sampling": "linear"}}, {"class_name": "Int", "config": {"name": "filters_9", "default": null, "conditions": [], "min_value": 32, "max_value": 256, "step": 32, "sampling": "linear"}}], "values": {"num_conv_layers": 9, "kernel_size_0": 6, "filters_0": 192, "kernel_size_1": 8, "filters_1": 256, "kernel_size_2": 4, "filters_2": 256, "kernel_size_3": 8, "filters_3": 192, "kernel_size_4": 9, "filters_4": 32, "kernel_size_5": 6, "filters_5": 128, "kernel_size_6": 5, "filters_6": 32, "kernel_size_7": 6, "filters_7": 96, "kernel_size_8": 5, "filters_8": 224, "kernel_size_9": 3, "filters_9": 96}}, "metrics": {"metrics": {"accuracy": {"direction": "max", "observations": [{"value": [0.8304263353347778], "step": 9}]}, "loss": {"direction": "min", "observations": [{"value": [0.4477556347846985], "step": 9}]}, "val_accuracy": {"direction": "max", "observations": [{"value": [0.7749999761581421], "step": 9}]}, "val_loss": {"direction": "min", "observations": [{"value": [0.6229919195175171], "step": 9}]}}}, "score": 0.7749999761581421, "best_step": 9, "status": "COMPLETED", "message": null}